sevent/__init__.py
sevent/buffer.py
sevent/cbuffer.cp314-win_amd64.pyd
sevent/dns.py
sevent/errors.py
sevent/event.py
sevent/loop.py
sevent/pipe.py
sevent/tcp.py
sevent/udp.py
sevent/utils.py
sevent/waker.py
sevent/win32util.py
sevent/coroutines/__init__.py
sevent/coroutines/chain.py
sevent/coroutines/dns.py
sevent/coroutines/event.py
sevent/coroutines/future.py
sevent/coroutines/loop.py
sevent/coroutines/pipe.py
sevent/coroutines/tcp.py
sevent/coroutines/udp.py
sevent/helpers/__init__.py
sevent/helpers/__main__.py
sevent/helpers/arproxy.py
sevent/helpers/proxy2proxy.py
sevent/helpers/proxy_tunnel.py
sevent/helpers/redirect2proxy.py
sevent/helpers/simple_proxy.py
sevent/helpers/tcp2proxy.py
sevent/helpers/tcp_forward.py
sevent/helpers/tcp_reverse.py
sevent/helpers/utils.py
sevent/impl/__init__.py
sevent/impl/epoll_loop.py
sevent/impl/kqueue_loop.py
sevent/impl/select_loop.py
sevent/sslsocket/__init__.py
sevent/sslsocket/tcp.py
sevent-0.4.41.dist-info/METADATA
sevent-0.4.41.dist-info/WHEEL
sevent-0.4.41.dist-info/top_level.txt
sevent-0.4.41.dist-info/RECORD
