Metadata-Version: 2.4
Name: sevent
Version: 0.4.41
Summary: lightweight event loop
Home-page: https://github.com/snower/sevent
Author: snower
Author-email: sujian199@gmail.com
License: MIT
Requires-Dist: dnslib>=0.9.7
Requires-Dist: greenlet>=0.4.2
Dynamic: author
Dynamic: author-email
Dynamic: description
Dynamic: description-content-type
Dynamic: home-page
Dynamic: license
Dynamic: requires-dist
Dynamic: summary
